gemgis_data/__init__.py
gemgis_data-0.0.2.dist-info/LICENSE
gemgis_data-0.0.2.dist-info/METADATA
gemgis_data-0.0.2.dist-info/WHEEL
gemgis_data-0.0.2.dist-info/top_level.txt
gemgis_data-0.0.2.dist-info/RECORD
