Metadata-Version: 2.1
Name: gemgis-data
Version: 0.0.2
Summary: GemGIS is a Python-based, open-source spatial data processing library.
Home-page: https://github.com/cgre-aachen/gemgis_data
Author: Alexander Jüstel, Miguel de la Varga, Nils Chudalla, Stefan Back, Florian Wellmann
Author-email: alexander.juestel@rwth-aachen.de
License: LGPL v3
Keywords: geology,geographic,structural geology,GIS,spatial data
License-File: LICENSE
